{
  "movies": [
    {
      "id": 1,
      "title": "Interstellar",
      "year": "2014",
      "picture": "https://upload.wikimedia.org/wikipedia/en/b/bc/Interstellar_film_poster.jpg",
      "director": "Christopher Nolan",
      "writers": [
        "Jonathan Nolan",
        "Christopher Nolan"
      ],
      "stars": [
        "Matthew McConaughey",
        "Anne Hathaway",
        "Jessica Chastain"
      ]
    },
    {
      "id": 3,
      "title": "Pulp Fiction",
      "year": "1994",
      "picture": "https://upload.wikimedia.org/wikipedia/en/3/3b/Pulp_Fiction_%281994%29_poster.jpg",
      "director": "Quentin Tarantino",
      "writers": [
        "Quentin Tarantino",
        "Roger Avary"
      ],
      "stars": [
        "John Travolta",
        "Uma Thurman",
        "Samuel L. Jackson"
      ]
    },
    {
      "id": 4,
      "title": "The Wolf of Wall Street",
      "year": "2013",
      "picture": "https://upload.wikimedia.org/wikipedia/en/d/d8/The_Wolf_of_Wall_Street_%282013%29.png",
      "director": "Martin Scorsese",
      "writers": [
        "Terence Winter",
        "Jordan Belfort"
      ],
      "stars": [
        "Leonardo DiCaprio",
        "Jonah Hill",
        "Margot Robbie"
      ]
    },
    {
      "id": 7,
      "title": "Rounders",
      "year": "1998",
      "picture": "https://upload.wikimedia.org/wikipedia/en/6/67/RoundersPoster.jpg",
      "director": "John Dahl",
      "writers": [
        "David Levien",
        "Brian Koppelman"
      ],
      "stars": [
        "Matt Damon",
        "Edward Norton",
        "Gretchen Mol"
      ]
    },
    {
      "id": 8,
      "title": "Forrest Gump",
      "year": "1995",
      "picture": "https://upload.wikimedia.org/wikipedia/en/6/67/Forrest_Gump_poster.jpg",
      "director": "Robert Zemeckis",
      "writers": [
        "Winston Groom",
        "Eric Roth",
        ""
      ],
      "stars": [
        "Tom Hanks",
        "Robin Wright",
        "Gary Sinise"
      ]
    },
    {
      "id": 9,
      "title": "American History X",
      "year": "1998",
      "picture": "https://upload.wikimedia.org/wikipedia/en/3/39/American_History_X_poster.png",
      "director": "Tony Kaye",
      "writers": [
        "David McKenna"
      ],
      "stars": [
        "Edward Norton",
        "Edward Furlong",
        "Beverly D'Angelo"
      ]
    },
    {
      "id": 10,
      "title": "Good Will Hunting",
      "year": "1998",
      "picture": "https://upload.wikimedia.org/wikipedia/en/5/52/Good_Will_Hunting.png",
      "director": "Gus Van Sant",
      "writers": [
        "Matt Damon",
        "Ben Affleck",
        ""
      ],
      "stars": [
        "Robin Williams",
        "Matt Damon",
        "Ben Affleck"
      ]
    },
    {
      "id": 11,
      "title": "Rocky",
      "year": "1981",
      "picture": "https://images-na.ssl-images-amazon.com/images/I/91Wz30TIWvL._RI_.jpg",
      "director": "John G. Avildsen",
      "writers": [
        "Sylvester Stallone",
        "John G. Avildsen",
        ""
      ],
      "stars": [
        "Sylvester Stallone",
        "",
        ""
      ]
    },
    {
      "id": 12,
      "title": "Rocky",
      "year": "1976",
      "picture": "https://images-na.ssl-images-amazon.com/images/I/91Wz30TIWvL._RI_.jpg",
      "director": "Sylvester Stallone",
      "writers": [
        "Sylvester Stallone",
        "John G. Avildsen",
        "Eric"
      ],
      "stars": [
        "Sylvester Stallone",
        "",
        ""
      ]
    },
    {
      "id": 13,
      "title": "Rocky",
      "year": "1976",
      "picture": "https://images-na.ssl-images-amazon.com/images/I/91Wz30TIWvL._RI_.jpg",
      "director": "Sylvester Stallone",
      "writers": [
        "Sylvester Stallone",
        "John G. Avildsen",
        ""
      ],
      "stars": [
        "Sylvester Stallone",
        "",
        ""
      ]
    }
  ]
}